intgr_pay_api-0.0.5.dist-info/DESCRIPTION.rst
intgr_pay_api-0.0.5.dist-info/METADATA
intgr_pay_api-0.0.5.dist-info/metadata.json
intgr_pay_api-0.0.5.dist-info/RECORD
intgr_pay_api-0.0.5.dist-info/top_level.txt
intgr_pay_api-0.0.5.dist-info/WHEEL
pay_api/classes.py
pay_api/conf.py
pay_api/models.py
pay_api/signals.py
pay_api/test.py
pay_api/views.py
pay_api/__init__.py
pay_api/backends/dotpay.py
pay_api/backends/paypal.py
pay_api/backends/payu.py
pay_api/backends/__init__.py
pay_api/migrations/__init__.py
project/settings.py
project/urls.py
project/wsgi.py
project/__init__.py
